energy_trading_api/__init__.py
energy_trading_api/australiaBOM.py
energy_trading_api/australiaLNG.py
energy_trading_api/australiaNG.py
energy_trading_api/australiaREC.py
energy_trading_api/australiaWEM.py
energy_trading_api/common.py
energy_trading_api/eia_api.py
energy_trading_api/japanElectricity.py
energy_trading_api/japanFEPC.py
energy_trading_api/jepx.py
energy_trading_api/singaporeNEMS.py
energy_trading_api/wagbb.py
energy_trading_api-0.0.34.dist-info/METADATA
energy_trading_api-0.0.34.dist-info/WHEEL
energy_trading_api-0.0.34.dist-info/top_level.txt
energy_trading_api-0.0.34.dist-info/RECORD
