Metadata-Version: 2.1
Name: energy-trading-api
Version: 0.0.34
Summary: API Wrappers for the Energy Markets
Home-page: https://github.com/jericmac/energy-trading-api-wrappers
Author: jericmac
Author-email: 
License: UNKNOWN
Platform: UNKNOWN
Classifier: Programming Language :: Python :: 3
Classifier: License :: OSI Approved :: MIT License
Classifier: Operating System :: OS Independent
Requires-Dist: eia-python (==1.22)
Requires-Dist: Scrapy (==1.6.0)
